Project/src/counter.v
module counter #(
    parameter WIDTH = 8
)(
    input  wire             clk,
    input  wire             rst,     // reset aktywny '1'
    output reg  [WIDTH-1:0] q
);

    always @(posedge clk or posedge rst) begin
        if (rst)
            q <= {WIDTH{1'b0}};
        else
            q <= q + 1'b1;
    end

endmodule

Project/tb/tb_counter.v
`timescale 1ns/1ps

module tb_counter;

    reg clk = 0;
    reg rst = 0;
    wire [7:0] q;

    counter #(.WIDTH(8)) dut (
        .clk(clk),
        .rst(rst),
        .q(q)
    );

    // 100 MHz
    always #5 clk = ~clk;

    initial begin
        $dumpfile("counter.vcd");
        $dumpvars(0, tb_counter);

        rst = 1;
        #30;
        rst = 0;

        #500;
        $finish;
    end

endmodule

Project/counter.vcd
$date
	Sun Dec 14 13:38:12 2025
$end
$version
	Icarus Verilog
$end
$timescale
	1ps
$end
$scope module tb_counter $end
$var wire 8 ! q [7:0] $end
$var reg 1 " clk $end
$var reg 1 # rst $end
$scope module dut $end
$var wire 1 " clk $end
$var wire 1 # rst $end
$var parameter 32 $ WIDTH $end
$var reg 8 % q [7:0] $end
$upscope $end
$upscope $end
$enddefinitions $end
$comment Show the parameter values. $end
$dumpall
b1000 $
$end
#0
$dumpvars
b0 %
1#
0"
b0 !
$end
#5000
1"
#10000
0"
#15000
1"
#20000
0"
#25000
1"
#30000
0"
0#
#35000
b1 !
b1 %
1"
#40000
0"
#45000
b10 !
b10 %
1"
#50000
0"
#55000
b11 !
b11 %
1"
#60000
0"
#65000
b100 !
b100 %
1"
#70000
0"
#75000
b101 !
b101 %
1"
#80000
0"
#85000
b110 !
b110 %
1"
#90000
0"
#95000
b111 !
b111 %
1"
#100000
0"
#105000
b1000 !
b1000 %
1"
#110000
0"
#115000
b1001 !
b1001 %
1"
#120000
0"
#125000
b1010 !
b1010 %
1"
#130000
0"
#135000
b1011 !
b1011 %
1"
#140000
0"
#145000
b1100 !
b1100 %
1"
#150000
0"
#155000
b1101 !
b1101 %
1"
#160000
0"
#165000
b1110 !
b1110 %
1"
#170000
0"
#175000
b1111 !
b1111 %
1"
#180000
0"
#185000
b10000 !
b10000 %
1"
#190000
0"
#195000
b10001 !
b10001 %
1"
#200000
0"
#205000
b10010 !
b10010 %
1"
#210000
0"
#215000
b10011 !
b10011 %
1"
#220000
0"
#225000
b10100 !
b10100 %
1"
#230000
0"
#235000
b10101 !
b10101 %
1"
#240000
0"
#245000
b10110 !
b10110 %
1"
#250000
0"
#255000
b10111 !
b10111 %
1"
#260000
0"
#265000
b11000 !
b11000 %
1"
#270000
0"
#275000
b11001 !
b11001 %
1"
#280000
0"
#285000
b11010 !
b11010 %
1"
#290000
0"
#295000
b11011 !
b11011 %
1"
#300000
0"
#305000
b11100 !
b11100 %
1"
#310000
0"
#315000
b11101 !
b11101 %
1"
#320000
0"
#325000
b11110 !
b11110 %
1"
#330000
0"
#335000
b11111 !
b11111 %
1"
#340000
0"
#345000
b100000 !
b100000 %
1"
#350000
0"
#355000
b100001 !
b100001 %
1"
#360000
0"
#365000
b100010 !
b100010 %
1"
#370000
0"
#375000
b100011 !
b100011 %
1"
#380000
0"
#385000
b100100 !
b100100 %
1"
#390000
0"
#395000
b100101 !
b100101 %
1"
#400000
0"
#405000
b100110 !
b100110 %
1"
#410000
0"
#415000
b100111 !
b100111 %
1"
#420000
0"
#425000
b101000 !
b101000 %
1"
#430000
0"
#435000
b101001 !
b101001 %
1"
#440000
0"
#445000
b101010 !
b101010 %
1"
#450000
0"
#455000
b101011 !
b101011 %
1"
#460000
0"
#465000
b101100 !
b101100 %
1"
#470000
0"
#475000
b101101 !
b101101 %
1"
#480000
0"
#485000
b101110 !
b101110 %
1"
#490000
0"
#495000
b101111 !
b101111 %
1"
#500000
0"
#505000
b110000 !
b110000 %
1"
#510000
0"
#515000
b110001 !
b110001 %
1"
#520000
0"
#525000
b110010 !
b110010 %
1"
